LICENSE
MANIFEST.in
README.md
setup.py
django_versioncheck.egg-info/PKG-INFO
django_versioncheck.egg-info/SOURCES.txt
django_versioncheck.egg-info/dependency_links.txt
django_versioncheck.egg-info/requires.txt
django_versioncheck.egg-info/top_level.txt
versioncheck/__init__.py
versioncheck/models.py
versioncheck/tests.py
versioncheck/urls.py
versioncheck/utils.py
versioncheck/views.py
versioncheck/management/__init__.py
versioncheck/management/commands/__init__.py
versioncheck/management/commands/checkversion.py