Metadata-Version: 1.1
Name: django-versioncheck
Version: 0.1.0
Summary: A small django app which tries to be annoying if your django version is outdated.
Home-page: https://github.com/noxan/django-versioncheck
Author: Richard Stromer
Author-email: noxan@byteweaver.org
License: BSD
Platform: UNKNOWN
Classifier: Development Status :: 2 - Pre-Alpha
Classifier: Environment :: Web Environment
Classifier: Framework :: Django
Classifier: Intended Audience :: Developers
Classifier: License :: OSI Approved :: BSD License
Classifier: Operating System :: OS Independent
Classifier: Programming Language :: Python
Classifier: Programming Language :: Python :: 3
